LICENSE
MANIFEST.in
README.rst
setup.py
django_security_logger.egg-info/PKG-INFO
django_security_logger.egg-info/SOURCES.txt
django_security_logger.egg-info/dependency_links.txt
django_security_logger.egg-info/not-zip-safe
django_security_logger.egg-info/requires.txt
django_security_logger.egg-info/top_level.txt
example/__init__.py
example/manage.py
example/test_elastic.py
example/urls.py
example/wsgi.py
example/apps/__init__.py
example/apps/test_security/__init__.py
example/apps/test_security/models.py
example/apps/test_security/tasks.py
example/apps/test_security/views.py
example/apps/test_security/management/__init__.py
example/apps/test_security/management/commands/__init__.py
example/apps/test_security/management/commands/create_user.py
example/apps/test_security/management/commands/create_users.py
example/apps/test_security/management/commands/test_command.py
example/apps/test_security/management/commands/test_command_with_response.py
example/apps/test_security/management/commands/test_error_command.py
example/apps/test_security/tests/__init__.py
example/apps/test_security/tests/base.py
example/apps/test_security/tests/celery_log.py
example/apps/test_security/tests/command_log.py
example/apps/test_security/tests/commands.py
example/apps/test_security/tests/input_request_log.py
example/apps/test_security/tests/output_request_log.py
example/apps/test_security/tests/throttling_validators.py
example/apps/test_security/tests/utils.py
example/settings/__init__.py
example/settings/base.py
example/settings/celery.py
example/settings/settings.py
security/__init__.py
security/apps.py
security/command.py
security/config.py
security/decorators.py
security/enums.py
security/log_context.py
security/middleware.py
security/models.py
security/requests.py
security/storages.py
security/suds.py
security/task.py
security/utils.py
security/version.py
security/backends/__init__.py
security/backends/app.py
security/backends/purge_logs.py
security/backends/reader.py
security/backends/signals.py
security/backends/writer.py
security/backends/common/__init__.py
security/backends/common/is_core.py
security/backends/common/mixins.py
security/backends/elasticsearch/__init__.py
security/backends/elasticsearch/app.py
